{
  "tailwindcss": {
    "name": "TailwindCSS",
    "modes": [{ "id": "default", "name": "Default" }],
    "variables": [
      { "name": "spacing/0", "type": "FLOAT", "value": 0, "description": "" },
      { "name": "spacing/1", "type": "FLOAT", "value": 4, "description": "" },
      { "name": "spacing/2", "type": "FLOAT", "value": 8, "description": "" },
      { "name": "spacing/3", "type": "FLOAT", "value": 12, "description": "" },
      { "name": "spacing/4", "type": "FLOAT", "value": 16, "description": "" },
      { "name": "spacing/5", "type": "FLOAT", "value": 20, "description": "" },
      { "name": "spacing/6", "type": "FLOAT", "value": 24, "description": "" },
      { "name": "spacing/7", "type": "FLOAT", "value": 28, "description": "" },
      { "name": "spacing/8", "type": "FLOAT", "value": 32, "description": "" },
      { "name": "spacing/9", "type": "FLOAT", "value": 36, "description": "" },
      { "name": "spacing/10", "type": "FLOAT", "value": 40, "description": "" },
      { "name": "spacing/11", "type": "FLOAT", "value": 44, "description": "" },
      { "name": "spacing/12", "type": "FLOAT", "value": 48, "description": "" },
      { "name": "spacing/14", "type": "FLOAT", "value": 56, "description": "" },
      { "name": "spacing/16", "type": "FLOAT", "value": 64, "description": "" },
      { "name": "spacing/20", "type": "FLOAT", "value": 80, "description": "" },
      { "name": "spacing/24", "type": "FLOAT", "value": 96, "description": "" },
      { "name": "spacing/28", "type": "FLOAT", "value": 112, "description": "" },
      { "name": "spacing/32", "type": "FLOAT", "value": 128, "description": "" },
      { "name": "spacing/36", "type": "FLOAT", "value": 144, "description": "" },
      { "name": "spacing/40", "type": "FLOAT", "value": 160, "description": "" },
      { "name": "spacing/44", "type": "FLOAT", "value": 176, "description": "" },
      { "name": "spacing/48", "type": "FLOAT", "value": 192, "description": "" },
      { "name": "spacing/52", "type": "FLOAT", "value": 208, "description": "" },
      { "name": "spacing/56", "type": "FLOAT", "value": 224, "description": "" },
      { "name": "spacing/60", "type": "FLOAT", "value": 240, "description": "" },
      { "name": "spacing/64", "type": "FLOAT", "value": 256, "description": "" },
      { "name": "spacing/72", "type": "FLOAT", "value": 288, "description": "" },
      { "name": "spacing/80", "type": "FLOAT", "value": 320, "description": "" },
      { "name": "spacing/96", "type": "FLOAT", "value": 384, "description": "" },

      { "name": "border-width/border-0", "type": "FLOAT", "value": 0, "description": "" },
      { "name": "border-width/border-1", "type": "FLOAT", "value": 1, "description": "" },
      { "name": "border-width/border-2", "type": "FLOAT", "value": 2, "description": "" },
      { "name": "border-width/border-4", "type": "FLOAT", "value": 4, "description": "" },
      { "name": "border-width/border-8", "type": "FLOAT", "value": 8, "description": "" },

      { "name": "border-radius/rounded-none", "type": "FLOAT", "value": 0, "description": "" },
      { "name": "border-radius/rounded-sm", "type": "FLOAT", "value": 2, "description": "" },
      { "name": "border-radius/rounded", "type": "FLOAT", "value": 4, "description": "" },
      { "name": "border-radius/rounded-md", "type": "FLOAT", "value": 6, "description": "" },
      { "name": "border-radius/rounded-lg", "type": "FLOAT", "value": 8, "description": "" },
      { "name": "border-radius/rounded-xl", "type": "FLOAT", "value": 12, "description": "" },
      { "name": "border-radius/rounded-2xl", "type": "FLOAT", "value": 16, "description": "" },
      { "name": "border-radius/rounded-3xl", "type": "FLOAT", "value": 24, "description": "" },
      { "name": "border-radius/rounded-full", "type": "FLOAT", "value": 9999, "description": "" },

      { "name": "opacity/opacity-0", "type": "FLOAT", "value": 0, "description": "" },
      { "name": "opacity/opacity-5", "type": "FLOAT", "value": 5, "description": "" },
      { "name": "opacity/opacity-10", "type": "FLOAT", "value": 10, "description": "" },
      { "name": "opacity/opacity-15", "type": "FLOAT", "value": 15, "description": "" },
      { "name": "opacity/opacity-20", "type": "FLOAT", "value": 20, "description": "" },
      { "name": "opacity/opacity-25", "type": "FLOAT", "value": 25, "description": "" },
      { "name": "opacity/opacity-30", "type": "FLOAT", "value": 30, "description": "" },
      { "name": "opacity/opacity-35", "type": "FLOAT", "value": 35, "description": "" },
      { "name": "opacity/opacity-40", "type": "FLOAT", "value": 40, "description": "" },
      { "name": "opacity/opacity-45", "type": "FLOAT", "value": 45, "description": "" },
      { "name": "opacity/opacity-50", "type": "FLOAT", "value": 50, "description": "" },
      { "name": "opacity/opacity-55", "type": "FLOAT", "value": 55, "description": "" },
      { "name": "opacity/opacity-60", "type": "FLOAT", "value": 60, "description": "" },
      { "name": "opacity/opacity-65", "type": "FLOAT", "value": 65, "description": "" },
      { "name": "opacity/opacity-70", "type": "FLOAT", "value": 70, "description": "" },
      { "name": "opacity/opacity-75", "type": "FLOAT", "value": 75, "description": "" },
      { "name": "opacity/opacity-80", "type": "FLOAT", "value": 80, "description": "" },
      { "name": "opacity/opacity-85", "type": "FLOAT", "value": 85, "description": "" },
      { "name": "opacity/opacity-90", "type": "FLOAT", "value": 90, "description": "" },
      { "name": "opacity/opacity-95", "type": "FLOAT", "value": 95, "description": "" },
      { "name": "opacity/opacity-100", "type": "FLOAT", "value": 100, "description": "" },

      { "name": "font-size/text-xs", "type": "FLOAT", "value": 12, "description": "" },
      { "name": "font-size/text-sm", "type": "FLOAT", "value": 14, "description": "" },
      { "name": "font-size/text-base", "type": "FLOAT", "value": 16, "description": "" },
      { "name": "font-size/text-lg", "type": "FLOAT", "value": 18, "description": "" },
      { "name": "font-size/text-xl", "type": "FLOAT", "value": 20, "description": "" },
      { "name": "font-size/text-2xl", "type": "FLOAT", "value": 24, "description": "" },
      { "name": "font-size/text-3xl", "type": "FLOAT", "value": 30, "description": "" },
      { "name": "font-size/text-4xl", "type": "FLOAT", "value": 36, "description": "" },
      { "name": "font-size/text-5xl", "type": "FLOAT", "value": 48, "description": "" },
      { "name": "font-size/text-6xl", "type": "FLOAT", "value": 60, "description": "" },
      { "name": "font-size/text-7xl", "type": "FLOAT", "value": 72, "description": "" },
      { "name": "font-size/text-8xl", "type": "FLOAT", "value": 96, "description": "" },
      { "name": "font-size/text-9xl", "type": "FLOAT", "value": 128, "description": "" },

      { "name": "font-weight/font-thin", "type": "FLOAT", "value": 100, "description": "" },
      { "name": "font-weight/font-extralight", "type": "FLOAT", "value": 200, "description": "" },
      { "name": "font-weight/font-light", "type": "FLOAT", "value": 300, "description": "" },
      { "name": "font-weight/font-normal", "type": "FLOAT", "value": 400, "description": "" },
      { "name": "font-weight/font-medium", "type": "FLOAT", "value": 500, "description": "" },
      { "name": "font-weight/font-semibold", "type": "FLOAT", "value": 600, "description": "" },
      { "name": "font-weight/font-bold", "type": "FLOAT", "value": 700, "description": "" },
      { "name": "font-weight/font-extrabold", "type": "FLOAT", "value": 800, "description": "" },
      { "name": "font-weight/font-black", "type": "FLOAT", "value": 900, "description": "" },

      { "name": "line-height/leading-none", "type": "FLOAT", "value": 1, "description": "" },
      { "name": "line-height/leading-tight", "type": "FLOAT", "value": 1.25, "description": "" },
      { "name": "line-height/leading-snug", "type": "FLOAT", "value": 1.375, "description": "" },
      { "name": "line-height/leading-normal", "type": "FLOAT", "value": 1.5, "description": "" },
      { "name": "line-height/leading-relaxed", "type": "FLOAT", "value": 1.625, "description": "" },
      { "name": "line-height/leading-loose", "type": "FLOAT", "value": 2, "description": "" }
    ]
  }
}
